pyizone/__init__.py
pyizone/__main__.py
pyizone/__pyizone__.py
mikenye_pyizone-0.1.dist-info/LICENSE
mikenye_pyizone-0.1.dist-info/METADATA
mikenye_pyizone-0.1.dist-info/WHEEL
mikenye_pyizone-0.1.dist-info/top_level.txt
mikenye_pyizone-0.1.dist-info/RECORD
