Metadata-Version: 2.1
Name: mikenye-pyizone
Version: 0.1
Summary: Query and control of WiFi-enabled iZone 310 and compatible family of climate control devices
Home-page: https://github.com/mikenye/pyizone
Author: Mike Nye
License: UNKNOWN
Platform: UNKNOWN
Classifier: Development Status :: 5 - Production/Stable
Classifier: Programming Language :: Python :: 3
Classifier: License :: OSI Approved :: The Unlicense (Unlicense)
Classifier: Operating System :: OS Independent
Classifier: Topic :: Home Automation
Requires-Python: >=3.5
